<?xml version="1.0" encoding="UTF-8"?>
<!--
Created with Funkin Packer v0.1.3 https://neeeoo.github.io/funkin-packer/
-->
<TextureAtlas imagePath="SaffIntro.png" width="7710" height="7612">
	<SubTexture name="SaffPresents0080" x="6" y="6" width="1920" height="1080" frameX="-0" frameY="-0" frameWidth="1920" frameHeight="1080"/>
	<SubTexture name="SaffPresents0081" x="6" y="1092" width="1920" height="1080" frameX="-0" frameY="-0" frameWidth="1920" frameHeight="1080"/>
	<SubTexture name="SaffPresents0082" x="1932" y="6" width="1920" height="616" frameX="-0" frameY="-243" frameWidth="1920" frameHeight="1080"/>
	<SubTexture name="SaffPresents0083" x="5784" y="4350" width="1866" height="324" frameX="-34" frameY="-389" frameWidth="1920" frameHeight="1080"/>
	<SubTexture name="SaffPresents0085" x="3034" y="6722" width="746" height="142" frameX="-594" frameY="-480" frameWidth="1920" frameHeight="1080"/>
	<SubTexture name="SaffPresents0087" x="2280" y="6722" width="748" height="142" frameX="-593" frameY="-480" frameWidth="1920" frameHeight="1080"/>
	<SubTexture name="SaffPresents0089" x="1524" y="6734" width="750" height="142" frameX="-592" frameY="-480" frameWidth="1920" frameHeight="1080"/>
	<SubTexture name="SaffPresents0091" x="766" y="6734" width="752" height="142" frameX="-591" frameY="-480" frameWidth="1920" frameHeight="1080"/>
	<SubTexture name="SaffPresents0093" x="6" y="6734" width="754" height="142" frameX="-590" frameY="-480" frameWidth="1920" frameHeight="1080"/>
	<SubTexture name="SaffPresents0095" x="6675" y="6356" width="756" height="142" frameX="-589" frameY="-480" frameWidth="1920" frameHeight="1080"/>
	<SubTexture name="SaffPresents0097" x="6339" y="6208" width="758" height="142" frameX="-588" frameY="-480" frameWidth="1920" frameHeight="1080"/>
	<SubTexture name="SaffPresents0099" x="6675" y="5912" width="760" height="142" frameX="-587" frameY="-480" frameWidth="1920" frameHeight="1080"/>
	<SubTexture name="SaffPresents0101" x="6339" y="6060" width="760" height="142" frameX="-587" frameY="-480" frameWidth="1920" frameHeight="1080"/>
	<SubTexture name="SaffPresents0105" x="6675" y="5766" width="762" height="140" frameX="-586" frameY="-481" frameWidth="1920" frameHeight="1080"/>
	<SubTexture name="SaffPresents0109" x="5880" y="6530" width="764" height="140" frameX="-585" frameY="-481" frameWidth="1920" frameHeight="1080"/>
	<SubTexture name="SaffPresents0113" x="6650" y="6530" width="764" height="140" frameX="-585" frameY="-481" frameWidth="1920" frameHeight="1080"/>
	<SubTexture name="SaffSong0141" x="1932" y="628" width="1920" height="1080" frameX="-0" frameY="-0" frameWidth="1920" frameHeight="1080"/>
	<SubTexture name="SaffSong0142" x="1932" y="1714" width="1920" height="1080" frameX="-0" frameY="-0" frameWidth="1920" frameHeight="1080"/>
	<SubTexture name="SaffSong0143" x="6" y="2178" width="1920" height="616" frameX="-0" frameY="-243" frameWidth="1920" frameHeight="1080"/>
	<SubTexture name="SaffSong0144" x="1901" y="5632" width="1536" height="324" frameX="-197" frameY="-389" frameWidth="1920" frameHeight="1080"/>
	<SubTexture name="SaffSong0146" x="631" y="7316" width="616" height="142" frameX="-658" frameY="-480" frameWidth="1920" frameHeight="1080"/>
	<SubTexture name="SaffSong0148" x="6" y="7316" width="619" height="142" frameX="-657" frameY="-480" frameWidth="1920" frameHeight="1080"/>
	<SubTexture name="SaffSong0150" x="6682" y="7120" width="621" height="142" frameX="-656" frameY="-480" frameWidth="1920" frameHeight="1080"/>
	<SubTexture name="SaffSong0152" x="6682" y="6972" width="623" height="142" frameX="-655" frameY="-480" frameWidth="1920" frameHeight="1080"/>
	<SubTexture name="SaffSong0154" x="6633" y="6824" width="624" height="142" frameX="-654" frameY="-480" frameWidth="1920" frameHeight="1080"/>
	<SubTexture name="SaffSong0156" x="6050" y="7012" width="626" height="142" frameX="-653" frameY="-480" frameWidth="1920" frameHeight="1080"/>
	<SubTexture name="SaffSong0158" x="6049" y="7162" width="627" height="142" frameX="-653" frameY="-480" frameWidth="1920" frameHeight="1080"/>
	<SubTexture name="SaffSong0160" x="5416" y="7014" width="628" height="142" frameX="-652" frameY="-480" frameWidth="1920" frameHeight="1080"/>
	<SubTexture name="SaffSong0162" x="5414" y="7162" width="629" height="142" frameX="-652" frameY="-480" frameWidth="1920" frameHeight="1080"/>
	<SubTexture name="SaffSong0166" x="4777" y="7162" width="631" height="140" frameX="-651" frameY="-481" frameWidth="1920" frameHeight="1080"/>
	<SubTexture name="SaffSong0170" x="4932" y="6868" width="632" height="140" frameX="-650" frameY="-481" frameWidth="1920" frameHeight="1080"/>
	<SubTexture name="SaffSong0174" x="4777" y="7016" width="633" height="140" frameX="-650" frameY="-481" frameWidth="1920" frameHeight="1080"/>
	<SubTexture name="BySaff0200" x="5784" y="3264" width="1871" height="1080" frameX="-49" frameY="-0" frameWidth="1920" frameHeight="1080"/>
	<SubTexture name="BySaff0201" x="5784" y="4680" width="1852" height="1080" frameX="-0" frameY="-0" frameWidth="1920" frameHeight="1080"/>
	<SubTexture name="BySaff0202" x="6" y="2800" width="1920" height="616" frameX="-0" frameY="-243" frameWidth="1920" frameHeight="1080"/>
	<SubTexture name="BySaff0203" x="1901" y="5302" width="1728" height="324" frameX="-106" frameY="-389" frameWidth="1920" frameHeight="1080"/>
	<SubTexture name="BySaff0205" x="4235" y="6868" width="691" height="142" frameX="-623" frameY="-480" frameWidth="1920" frameHeight="1080"/>
	<SubTexture name="BySaff0207" x="3535" y="6870" width="694" height="142" frameX="-621" frameY="-480" frameWidth="1920" frameHeight="1080"/>
	<SubTexture name="BySaff0209" x="2833" y="6870" width="696" height="142" frameX="-620" frameY="-480" frameWidth="1920" frameHeight="1080"/>
	<SubTexture name="BySaff0211" x="2129" y="6882" width="698" height="142" frameX="-619" frameY="-480" frameWidth="1920" frameHeight="1080"/>
	<SubTexture name="BySaff0213" x="1423" y="6882" width="700" height="142" frameX="-618" frameY="-480" frameWidth="1920" frameHeight="1080"/>
	<SubTexture name="BySaff0215" x="715" y="6882" width="702" height="142" frameX="-617" frameY="-480" frameWidth="1920" frameHeight="1080"/>
	<SubTexture name="BySaff0217" x="6" y="6882" width="703" height="142" frameX="-617" frameY="-480" frameWidth="1920" frameHeight="1080"/>
	<SubTexture name="BySaff0219" x="6641" y="6676" width="704" height="142" frameX="-616" frameY="-480" frameWidth="1920" frameHeight="1080"/>
	<SubTexture name="BySaff0221" x="5929" y="6676" width="706" height="142" frameX="-615" frameY="-480" frameWidth="1920" frameHeight="1080"/>
	<SubTexture name="BySaff0225" x="4501" y="6722" width="708" height="140" frameX="-614" frameY="-481" frameWidth="1920" frameHeight="1080"/>
	<SubTexture name="BySaff0229" x="5215" y="6722" width="708" height="140" frameX="-614" frameY="-481" frameWidth="1920" frameHeight="1080"/>
	<SubTexture name="BySaff0233" x="3786" y="6722" width="709" height="140" frameX="-614" frameY="-481" frameWidth="1920" frameHeight="1080"/>
	<SubTexture name="Feacher0266" x="1932" y="2800" width="1920" height="1080" frameX="-0" frameY="-0" frameWidth="1920" frameHeight="1080"/>
	<SubTexture name="Feacher0267" x="3858" y="6" width="1920" height="1080" frameX="-0" frameY="-0" frameWidth="1920" frameHeight="1080"/>
	<SubTexture name="Feacher0268" x="3858" y="1092" width="1920" height="610" frameX="-0" frameY="-249" frameWidth="1920" frameHeight="1080"/>
	<SubTexture name="Feacher0269" x="3299" y="6052" width="1303" height="324" frameX="-316" frameY="-389" frameWidth="1920" frameHeight="1080"/>
	<SubTexture name="Feacher0270" x="5929" y="6824" width="698" height="182" frameX="-618" frameY="-460" frameWidth="1920" frameHeight="1080"/>
	<SubTexture name="Feacher0272" x="4477" y="7310" width="527" height="142" frameX="-704" frameY="-480" frameWidth="1920" frameHeight="1080"/>
	<SubTexture name="Feacher0274" x="3943" y="7310" width="528" height="142" frameX="-703" frameY="-480" frameWidth="1920" frameHeight="1080"/>
	<SubTexture name="Feacher0276" x="3408" y="7316" width="529" height="142" frameX="-703" frameY="-480" frameWidth="1920" frameHeight="1080"/>
	<SubTexture name="Feacher0278" x="2871" y="7316" width="531" height="142" frameX="-702" frameY="-480" frameWidth="1920" frameHeight="1080"/>
	<SubTexture name="Feacher0280" x="2333" y="7316" width="532" height="142" frameX="-701" frameY="-480" frameWidth="1920" frameHeight="1080"/>
	<SubTexture name="Feacher0282" x="1794" y="7316" width="533" height="142" frameX="-701" frameY="-480" frameWidth="1920" frameHeight="1080"/>
	<SubTexture name="Feacher0284" x="7105" y="6060" width="535" height="142" frameX="-700" frameY="-480" frameWidth="1920" frameHeight="1080"/>
	<SubTexture name="Feacher0286" x="1253" y="7316" width="535" height="142" frameX="-700" frameY="-480" frameWidth="1920" frameHeight="1080"/>
	<SubTexture name="Feacher0288" x="7103" y="6208" width="536" height="142" frameX="-699" frameY="-480" frameWidth="1920" frameHeight="1080"/>
	<SubTexture name="Sweet0297" x="3858" y="1708" width="1920" height="1080" frameX="-0" frameY="-0" frameWidth="1920" frameHeight="1080"/>
	<SubTexture name="Sweet0298" x="3858" y="2794" width="1920" height="1080" frameX="-0" frameY="-0" frameWidth="1920" frameHeight="1080"/>
	<SubTexture name="Sweet0299" x="1685" y="6052" width="1608" height="616" frameX="-167" frameY="-243" frameWidth="1920" frameHeight="1080"/>
	<SubTexture name="Sweet0300" x="5507" y="6052" width="826" height="324" frameX="-556" frameY="-389" frameWidth="1920" frameHeight="1080"/>
	<SubTexture name="Sweet0301" x="7211" y="7268" width="448" height="182" frameX="-744" frameY="-460" frameWidth="1920" frameHeight="1080"/>
	<SubTexture name="Sweet0302" x="2084" y="7464" width="339" height="142" frameX="-798" frameY="-480" frameWidth="1920" frameHeight="1080"/>
	<SubTexture name="Sweet0303" x="700" y="7464" width="340" height="142" frameX="-798" frameY="-480" frameWidth="1920" frameHeight="1080"/>
	<SubTexture name="Sweet0304" x="1046" y="7464" width="340" height="142" frameX="-798" frameY="-480" frameWidth="1920" frameHeight="1080"/>
	<SubTexture name="Sweet0305" x="1392" y="7464" width="340" height="142" frameX="-798" frameY="-480" frameWidth="1920" frameHeight="1080"/>
	<SubTexture name="Sweet0306" x="1738" y="7464" width="340" height="142" frameX="-798" frameY="-480" frameWidth="1920" frameHeight="1080"/>
	<SubTexture name="Sweet0307" x="6" y="7464" width="341" height="142" frameX="-797" frameY="-480" frameWidth="1920" frameHeight="1080"/>
	<SubTexture name="Sweet0308" x="353" y="7464" width="341" height="142" frameX="-797" frameY="-480" frameWidth="1920" frameHeight="1080"/>
	<SubTexture name="Sweet0309" x="7351" y="6676" width="342" height="142" frameX="-797" frameY="-480" frameWidth="1920" frameHeight="1080"/>
	<SubTexture name="Sweet0310" x="7311" y="6970" width="342" height="142" frameX="-797" frameY="-480" frameWidth="1920" frameHeight="1080"/>
	<SubTexture name="Sweet0311" x="6219" y="7310" width="342" height="142" frameX="-797" frameY="-480" frameWidth="1920" frameHeight="1080"/>
	<SubTexture name="Dad0322" x="6" y="3422" width="1920" height="1080" frameX="-0" frameY="-0" frameWidth="1920" frameHeight="1080"/>
	<SubTexture name="Dad0323" x="3858" y="3880" width="1920" height="1080" frameX="-0" frameY="-0" frameWidth="1920" frameHeight="1080"/>
	<SubTexture name="Dad0324" x="6" y="5130" width="1889" height="604" frameX="-25" frameY="-249" frameWidth="1920" frameHeight="1080"/>
	<SubTexture name="Dad0325" x="3299" y="6382" width="971" height="318" frameX="-482" frameY="-392" frameWidth="1920" frameHeight="1080"/>
	<SubTexture name="Dad0326" x="6682" y="7268" width="523" height="180" frameX="-706" frameY="-461" frameWidth="1920" frameHeight="1080"/>
	<SubTexture name="Dad0327" x="7309" y="7120" width="395" height="140" frameX="-770" frameY="-481" frameWidth="1920" frameHeight="1080"/>
	<SubTexture name="Dad0329" x="5817" y="7310" width="396" height="140" frameX="-769" frameY="-481" frameWidth="1920" frameHeight="1080"/>
	<SubTexture name="Dad0331" x="5414" y="7310" width="397" height="140" frameX="-769" frameY="-481" frameWidth="1920" frameHeight="1080"/>
	<SubTexture name="Dad0333" x="5010" y="7308" width="398" height="140" frameX="-768" frameY="-481" frameWidth="1920" frameHeight="1080"/>
	<SubTexture name="Dad0335" x="3443" y="5778" width="399" height="140" frameX="-768" frameY="-481" frameWidth="1920" frameHeight="1080"/>
	<SubTexture name="Dad0337" x="7263" y="6824" width="400" height="140" frameX="-767" frameY="-481" frameWidth="1920" frameHeight="1080"/>
	<SubTexture name="Dad0339" x="3443" y="5632" width="400" height="140" frameX="-767" frameY="-481" frameWidth="1920" frameHeight="1080"/>
	<SubTexture name="ThatGuy0355" x="1932" y="3886" width="1920" height="1080" frameX="-0" frameY="-0" frameWidth="1920" frameHeight="1080"/>
	<SubTexture name="ThatGuy0356" x="3858" y="4966" width="1920" height="1080" frameX="-0" frameY="-0" frameWidth="1920" frameHeight="1080"/>
	<SubTexture name="ThatGuy0357" x="6" y="4508" width="1920" height="616" frameX="-0" frameY="-243" frameWidth="1920" frameHeight="1080"/>
	<SubTexture name="ThatGuy0358" x="1932" y="4972" width="1920" height="324" frameX="-0" frameY="-389" frameWidth="1920" frameHeight="1080"/>
	<SubTexture name="ThatGuy0359" x="6" y="5740" width="1052" height="182" frameX="-440" frameY="-460" frameWidth="1920" frameHeight="1080"/>
	<SubTexture name="ThatGuy0361" x="5880" y="6382" width="789" height="142" frameX="-572" frameY="-480" frameWidth="1920" frameHeight="1080"/>
	<SubTexture name="ThatGuy0363" x="5081" y="6426" width="793" height="142" frameX="-570" frameY="-480" frameWidth="1920" frameHeight="1080"/>
	<SubTexture name="ThatGuy0365" x="5079" y="6574" width="795" height="142" frameX="-569" frameY="-480" frameWidth="1920" frameHeight="1080"/>
	<SubTexture name="ThatGuy0367" x="4276" y="6574" width="797" height="142" frameX="-568" frameY="-480" frameWidth="1920" frameHeight="1080"/>
	<SubTexture name="ThatGuy0369" x="4276" y="6426" width="799" height="142" frameX="-567" frameY="-480" frameWidth="1920" frameHeight="1080"/>
	<SubTexture name="ThatGuy0371" x="5784" y="5766" width="801" height="142" frameX="-566" frameY="-480" frameWidth="1920" frameHeight="1080"/>
	<SubTexture name="ThatGuy0373" x="1064" y="5888" width="803" height="142" frameX="-565" frameY="-480" frameWidth="1920" frameHeight="1080"/>
	<SubTexture name="ThatGuy0375" x="1064" y="5740" width="805" height="142" frameX="-564" frameY="-480" frameWidth="1920" frameHeight="1080"/>
	<SubTexture name="Important0384" x="5784" y="6" width="1920" height="1080" frameX="-0" frameY="-0" frameWidth="1920" frameHeight="1080"/>
	<SubTexture name="Important0385" x="5784" y="1092" width="1920" height="1080" frameX="-0" frameY="-0" frameWidth="1920" frameHeight="1080"/>
	<SubTexture name="Important0386" x="5784" y="2178" width="1920" height="1080" frameX="-0" frameY="-0" frameWidth="1920" frameHeight="1080"/>
	<SubTexture name="Important0387" x="6" y="6052" width="1673" height="676" frameX="-130" frameY="-213" frameWidth="1920" frameHeight="1080"/>
	<SubTexture name="Important0388" x="4608" y="6052" width="893" height="368" frameX="-520" frameY="-367" frameWidth="1920" frameHeight="1080"/>
	<SubTexture name="Important0389" x="4101" y="7018" width="670" height="280" frameX="-631" frameY="-411" frameWidth="1920" frameHeight="1080"/>
	<SubTexture name="Important0391" x="3423" y="7018" width="672" height="280" frameX="-630" frameY="-411" frameWidth="1920" frameHeight="1080"/>
	<SubTexture name="Important0393" x="2743" y="7030" width="674" height="280" frameX="-629" frameY="-411" frameWidth="1920" frameHeight="1080"/>
	<SubTexture name="Important0395" x="2061" y="7030" width="676" height="278" frameX="-628" frameY="-412" frameWidth="1920" frameHeight="1080"/>
	<SubTexture name="Important0397" x="1378" y="7030" width="677" height="278" frameX="-628" frameY="-412" frameWidth="1920" frameHeight="1080"/>
	<SubTexture name="Important0399" x="693" y="7030" width="679" height="278" frameX="-627" frameY="-412" frameWidth="1920" frameHeight="1080"/>
	<SubTexture name="Important0401" x="6" y="7030" width="681" height="278" frameX="-626" frameY="-412" frameWidth="1920" frameHeight="1080"/>
</TextureAtlas>