{
	"animations": [
		{
			"offsets": [
				0,
				0
			],
			"loop": false,
			"fps": 24,
			"anim": "idle",
			"indices": [],
			"name": "Bitter Idle"
		},
		{
			"offsets": [
				39,
				-8
			],
			"loop": false,
			"fps": 24,
			"anim": "singLEFT",
			"indices": [],
			"name": "Bitter Left"
		},
		{
			"offsets": [
				46,
				-4
			],
			"loop": false,
			"fps": 24,
			"anim": "singRIGHT",
			"indices": [],
			"name": "Bitter Right"
		},
		{
			"offsets": [
				-24,
				-76
			],
			"loop": false,
			"fps": 24,
			"anim": "singDOWN",
			"indices": [],
			"name": "Bitter Down"
		},
		{
			"offsets": [
				66,
				60
			],
			"loop": false,
			"fps": 24,
			"anim": "singUP",
			"indices": [],
			"name": "Bitter Up"
		},
		{
			"offsets": [
				0,
				0
			],
			"loop": false,
			"fps": 24,
			"anim": "idle-alt",
			"indices": [],
			"name": "Bitter Angry Idle"
		},
		{
			"offsets": [
				38,
				-1
			],
			"loop": false,
			"fps": 24,
			"anim": "singLEFT-alt",
			"indices": [],
			"name": "Bitter Angry Left"
		},
		{
			"offsets": [
				-22,
				-76
			],
			"loop": false,
			"fps": 24,
			"anim": "singDOWN-alt",
			"indices": [],
			"name": "Bitter Angry Down"
		},
		{
			"offsets": [
				46,
				-3
			],
			"loop": false,
			"fps": 24,
			"anim": "singRIGHT-alt",
			"indices": [],
			"name": "Bitter Angry Right"
		},
		{
			"offsets": [
				60,
				59
			],
			"loop": false,
			"fps": 24,
			"anim": "singUP-alt",
			"indices": [],
			"name": "Bitter Angry Up"
		},
		{
			"loop": false,
			"offsets": [
				50,
				-5
			],
			"anim": "singLEFTmiss",
			"fps": 24,
			"name": "Bitter Miss Left",
			"indices": []
		},
		{
			"loop": false,
			"offsets": [
				36,
				-3
			],
			"anim": "singRIGHTmiss",
			"fps": 24,
			"name": "Bitter Miss Right",
			"indices": []
		},
		{
			"loop": false,
			"offsets": [
				-21,
				-94
			],
			"anim": "singDOWNmiss",
			"fps": 24,
			"name": "Bitter Miss Down",
			"indices": []
		},
		{
			"loop": false,
			"offsets": [
				59,
				60
			],
			"anim": "singUPmiss",
			"fps": 24,
			"name": "Bitter Miss Up",
			"indices": []
		}
	],
	"no_antialiasing": false,
	"image": "characters/bitter",
	"position": [
		0,
		-120
	],
	"healthicon": "bitter",
	"flip_x": false,
	"healthbar_colors": [
		137,
		178,
		134
	],
	"camera_position": [
		0,
		20
	],
	"sing_duration": 6,
	"scale": 1,
	"noteskin": "Bitter",
	"healthbar_image": "Bitter",
	"musicNoteOffset": [-100,-400]
}